blinkpy/__init__.py
blinkpy/api.py
blinkpy/auth.py
blinkpy/blinkpy.py
blinkpy/camera.py
blinkpy/livestream.py
blinkpy/sync_module.py
blinkpy/helpers/__init__.py
blinkpy/helpers/constants.py
blinkpy/helpers/errors.py
blinkpy/helpers/oauth_parser.py
blinkpy/helpers/pkce.py
blinkpy/helpers/util.py
blinkpy-0.25.3.dist-info/licenses/LICENSE.md
blinkpy-0.25.3.dist-info/METADATA
blinkpy-0.25.3.dist-info/WHEEL
blinkpy-0.25.3.dist-info/top_level.txt
blinkpy-0.25.3.dist-info/RECORD
