Metadata-Version: 2.4
Name: blinkpy
Version: 0.25.3
Summary: A Blink camera Python Library.
Author-email: Kevin Fronczak <kfronczak@gmail.com>
License: MIT
Project-URL: Source Code, https://github.com/fronzbot/blinkpy
Project-URL: Bug Reports, https://github.com/fronzbot/blinkpy/issues
Platform: any
Classifier: Intended Audience :: Developers
Classifier: License :: OSI Approved :: MIT License
Classifier: Operating System :: OS Independent
Classifier: Programming Language :: Python :: 3.9
Classifier: Programming Language :: Python :: 3.10
Classifier: Programming Language :: Python :: 3.11
Classifier: Programming Language :: Python :: 3.12
Classifier: Programming Language :: Python :: 3.13
Classifier: Programming Language :: Python :: 3.14
Classifier: Topic :: Home Automation
Requires-Python: >=3.9.0
License-File: LICENSE.md
Requires-Dist: python-dateutil>=2.8.1
Requires-Dist: requests>=2.24.0
Requires-Dist: python-slugify>=4.0.1
Requires-Dist: sortedcontainers~=2.4.0
Requires-Dist: aiohttp>=3.8.4
Requires-Dist: aiofiles>=23.1.0
Dynamic: license-file
